README.rst
setup.py
fdsnwsscripts/__init__.py
fdsnwsscripts/fdsnavail.py
fdsnwsscripts/fdsnws2sds.py
fdsnwsscripts/fdsnws2seed.py
fdsnwsscripts/fdsnws_fetch.py
fdsnwsscripts/fdsnxml2arclink.py
fdsnwsscripts/test_fdsnavail.py
fdsnwsscripts.egg-info/PKG-INFO
fdsnwsscripts.egg-info/SOURCES.txt
fdsnwsscripts.egg-info/dependency_links.txt
fdsnwsscripts.egg-info/entry_points.txt
fdsnwsscripts.egg-info/requires.txt
fdsnwsscripts.egg-info/top_level.txt
fdsnwsscripts/seiscomp/__init__.py
fdsnwsscripts/seiscomp/fdsnxml.py
fdsnwsscripts/seiscomp/fseed.py
fdsnwsscripts/seiscomp/logs.py
fdsnwsscripts/seiscomp/mseedlite.py
fdsnwsscripts/seiscomp/db/__init__.py
fdsnwsscripts/seiscomp/db/generic/__init__.py
fdsnwsscripts/seiscomp/db/generic/inventory.py
fdsnwsscripts/seiscomp/db/xmlio/__init__.py
fdsnwsscripts/seiscomp/db/xmlio/inventory.py
fdsnwsscripts/seiscomp/db/xmlio/xmlwrap.py