Metadata-Version: 1.2
Name: fdsnwsscripts
Version: 2025.286
Summary: fdsnwsscripts: Scripts for working with (EIDA) FDSN web services
Home-page: https://geofon.gfz-potsdam.de/software/fdsnws_scripts
Author: Andres Heinloo
Author-email: andres@gfz-potsdam.de
License: GPLv3
Keywords: seismology waveforms federation fdsn-ws
Platform: UNKNOWN
Classifier: Development Status :: 4 - Beta
Classifier: Environment :: Console
Classifier: Intended Audience :: Science/Research
Classifier: License :: OSI Approved :: GNU Lesser General Public License v3 (LGPLv3)
Classifier: Natural Language :: English
Classifier: Operating System :: POSIX :: Linux
Classifier: Programming Language :: Python :: 3
Classifier: Topic :: Scientific/Engineering
Provides: fdsnwsscripts
Requires-Python: >=3
